close_bullet/__init__.py
close_bullet/Z1/__init__.py
close_bullet/Z1/captcha.py
close_bullet/Z1/external.py
close_bullet/Z1/library.py
close_bullet/Z1/options.py
close_bullet/backend/Data.py
close_bullet/backend/__init__.py
close_bullet/backend/general.py
close_bullet/backend/security.py
close_bullet-1.0.dist-info/METADATA
close_bullet-1.0.dist-info/WHEEL
close_bullet-1.0.dist-info/top_level.txt
close_bullet-1.0.dist-info/RECORD
