Metadata-Version: 2.1
Name: close-bullet
Version: 1.0
Summary: Privet Library For 01 Team
Author: NoBody_cp
Requires-Dist: requests
Requires-Dist: WMI
Requires-Dist: pystyle
Requires-Dist: pycountry
Requires-Dist: phonenumbers
Requires-Dist: nopecha
Requires-Dist: names
Requires-Dist: colorama
Requires-Dist: phone-iso3166
Requires-Dist: 1stcaptcha
